odoo/addons/sale_elaboration/README.rst
odoo/addons/sale_elaboration/__init__.py
odoo/addons/sale_elaboration/__manifest__.py
odoo/addons/sale_elaboration/hooks.py
odoo/addons/sale_elaboration/demo/sale_elaboration_demo.xml
odoo/addons/sale_elaboration/i18n/de.po
odoo/addons/sale_elaboration/i18n/es.po
odoo/addons/sale_elaboration/i18n/it.po
odoo/addons/sale_elaboration/i18n/sale_elaboration.pot
odoo/addons/sale_elaboration/models/__init__.py
odoo/addons/sale_elaboration/models/product.py
odoo/addons/sale_elaboration/models/product_category.py
odoo/addons/sale_elaboration/models/product_elaboration.py
odoo/addons/sale_elaboration/models/product_elaboration_mixin.py
odoo/addons/sale_elaboration/models/product_elaboration_profile.py
odoo/addons/sale_elaboration/models/product_template.py
odoo/addons/sale_elaboration/models/res_config_settings.py
odoo/addons/sale_elaboration/models/sale_order.py
odoo/addons/sale_elaboration/models/stock_move.py
odoo/addons/sale_elaboration/models/stock_picking.py
odoo/addons/sale_elaboration/models/stock_rule.py
odoo/addons/sale_elaboration/readme/CONFIGURE.md
odoo/addons/sale_elaboration/readme/CONTEXT.md
odoo/addons/sale_elaboration/readme/CONTRIBUTORS.md
odoo/addons/sale_elaboration/readme/DESCRIPTION.md
odoo/addons/sale_elaboration/readme/USAGE.md
odoo/addons/sale_elaboration/reports/report_base.xml
odoo/addons/sale_elaboration/reports/report_deliveryslip.xml
odoo/addons/sale_elaboration/reports/report_picking_operations.xml
odoo/addons/sale_elaboration/security/ir.model.access.csv
odoo/addons/sale_elaboration/security/security.xml
odoo/addons/sale_elaboration/static/description/icon.png
odoo/addons/sale_elaboration/static/description/index.html
odoo/addons/sale_elaboration/tests/__init__.py
odoo/addons/sale_elaboration/tests/test_sale_elaboration.py
odoo/addons/sale_elaboration/views/product_category_views.xml
odoo/addons/sale_elaboration/views/product_views.xml
odoo/addons/sale_elaboration/views/res_config_settings_views.xml
odoo_addon_sale_elaboration-18.0.1.0.2.1.dist-info/METADATA
odoo_addon_sale_elaboration-18.0.1.0.2.1.dist-info/WHEEL
odoo_addon_sale_elaboration-18.0.1.0.2.1.dist-info/top_level.txt
odoo_addon_sale_elaboration-18.0.1.0.2.1.dist-info/RECORD
